{"lineCoverageDisplay":{"default":{"value":"Select"},"PALiabilityCov_MIG":{"value":"Select"},"PAMedPayCov_MIG":{"value":"Select"},"PAUMBICovGA_MIG":{"value":"Select"},"PAUMPDPolCov_MIG":{"value":"Select"}},"lineCoverageTermDisplay":{"default":{"value":"Select"},"PAUMBICovGALimit_MIG":{"value":"Select"},"PAUMBI_GACovType_MIG":{"value":"Radio"},"PAUMPDPolCovDeduct_MIG":{"value":"LineItemSelect"}},"vehicleCoverageDisplay":{"default":{"value":"Select"},"PAComprehensiveCov_MIG":{"value":"Select"},"PACollisionCov_MIG":{"value":"Select"},"PACDWCov_MIG":{"value":"Select"},"PARentalCov_MIG":{"value":"Select"},"PARoadSideAssistance_MIG":{"value":"Select"},"PATowingLaborCov_MIG":{"value":"Select"},"PATransExpCov_MIG":{"value":"Select"},"PAOtherThanCollCov_MIG":{"value":"Select"},"PANonFactoryEquipment_MIG":{"value":"ReadOnly"},"PACustomExcEquipCov_MIG":{"value":"ReadOnly"}}}